neadva/Config.py
neadva/Request.py
neadva/Util.py
neadva/__init__.py
neadva/xsd/3.0/catalog.xml
neadva/xsd/3.0/common.xsd
neadva/xsd/3.0/invoiceAnnulment.xsd
neadva/xsd/3.0/invoiceApi.xsd
neadva/xsd/3.0/invoiceBase.xsd
neadva/xsd/3.0/invoiceData.xsd
neadva/xsd/3.0/serviceMetrics.xsd
neadva-0.52.dist-info/LICENSE
neadva-0.52.dist-info/METADATA
neadva-0.52.dist-info/WHEEL
neadva-0.52.dist-info/top_level.txt
neadva-0.52.dist-info/RECORD
