Metadata-Version: 2.1
Name: neadva
Version: 0.52
Summary: Hungarian Tax Authority NAV reporting api library
Home-page: https://github.com/ServerAstra/neadva
Download-URL: https://github.com/ServerAstra/neadva/archive/v0.52-alpha.tar.gz
Author: Andrew Azarov
Author-email: andrew@serverastra.com
License: MIT
Keywords: tax,hungary,reporting,api
Classifier: Development Status :: 3 - Alpha
Classifier: Intended Audience :: Developers
Classifier: Topic :: Internet :: WWW/HTTP
Classifier: Topic :: Office/Business :: Financial :: Accounting
Classifier: Topic :: Software Development :: Libraries :: Python Modules
Classifier: License :: OSI Approved :: MIT License
Classifier: Programming Language :: Python :: 3
License-File: LICENSE
Requires-Dist: pycryptodome
Requires-Dist: requests
Requires-Dist: pybase62
Requires-Dist: lxml
